[
  {
    "workspace": {
      "id": "e4bba9b3-8575-43e6-b9e2-e51434989984",
      "name": "irron2004's Projects"
    },
    "id": "9845a81a-7d5f-401f-b851-b13b2dda5a3d",
    "name": "ruahverce-hub",
    "createdAt": "2026-02-15T00:24:39.584Z",
    "updatedAt": "2026-03-16T15:37:17.193Z",
    "deletedAt": null,
    "environments": {
      "edges": [
        {
          "node": {
            "id": "844b87d4-ff05-474d-b733-8422bc413b11",
            "name": "production",
            "canAccess": true,
            "serviceInstances": {
              "edges": [
                {
                  "node": {
                    "serviceId": "faca3a67-9391-46c2-b2d0-2a7b978f1bfd"
                  }
                },
                {
                  "node": {
                    "serviceId": "a55885ae-6cf4-401c-a722-b17a282f59ca"
                  }
                }
              ]
            }
          }
        }
      ]
    },
    "services": {
      "edges": [
        {
          "node": {
            "id": "a55885ae-6cf4-401c-a722-b17a282f59ca",
            "name": "ruahverce-hub"
          }
        },
        {
          "node": {
            "id": "faca3a67-9391-46c2-b2d0-2a7b978f1bfd",
            "name": "coinlab-hub"
          }
        }
      ]
    }
  },
  {
    "workspace": {
      "id": "e4bba9b3-8575-43e6-b9e2-e51434989984",
      "name": "irron2004's Projects"
    },
    "id": "f6eaa074-88ea-467c-a0e5-4eb09a878966",
    "name": "pputty",
    "createdAt": "2025-07-03T03:57:52.577Z",
    "updatedAt": "2026-03-16T00:27:50.718Z",
    "deletedAt": null,
    "environments": {
      "edges": [
        {
          "node": {
            "id": "5bc8f712-a441-484b-a7d7-491455ba6341",
            "name": "production",
            "canAccess": true,
            "serviceInstances": {
              "edges": [
                {
                  "node": {
                    "serviceId": "b97fd6b4-2deb-46fd-ad25-a8af16be0417"
                  }
                },
                {
                  "node": {
                    "serviceId": "ce2449ec-d887-49fd-86a1-0466cb19c23f"
                  }
                },
                {
                  "node": {
                    "serviceId": "0ef522f0-3112-4198-8d08-92f3bc9ab62e"
                  }
                },
                {
                  "node": {
                    "serviceId": "a4cd1910-ab36-47de-be07-bf327e5d667a"
                  }
                },
                {
                  "node": {
                    "serviceId": "b3535f0e-eb29-44aa-8f84-5124138bb31a"
                  }
                },
                {
                  "node": {
                    "serviceId": "7b399d9c-ccfc-4513-801a-7b041da80445"
                  }
                },
                {
                  "node": {
                    "serviceId": "129ded4e-bad0-4036-ae40-f1fe77b0e496"
                  }
                }
              ]
            }
          }
        }
      ]
    },
    "services": {
      "edges": [
        {
          "node": {
            "id": "0ef522f0-3112-4198-8d08-92f3bc9ab62e",
            "name": "ruahverce-hub"
          }
        },
        {
          "node": {
            "id": "129ded4e-bad0-4036-ae40-f1fe77b0e496",
            "name": "calculate_math"
          }
        },
        {
          "node": {
            "id": "7b399d9c-ccfc-4513-801a-7b041da80445",
            "name": "calculate_math_frontend_gh"
          }
        },
        {
          "node": {
            "id": "a4cd1910-ab36-47de-be07-bf327e5d667a",
            "name": "calculate_math_frontend"
          }
        },
        {
          "node": {
            "id": "b3535f0e-eb29-44aa-8f84-5124138bb31a",
            "name": "calculate_math_neo4j"
          }
        },
        {
          "node": {
            "id": "b97fd6b4-2deb-46fd-ad25-a8af16be0417",
            "name": "english_egg"
          }
        },
        {
          "node": {
            "id": "ce2449ec-d887-49fd-86a1-0466cb19c23f",
            "name": "if_i_were_you_fix"
          }
        }
      ]
    }
  },
  {
    "workspace": {
      "id": "e4bba9b3-8575-43e6-b9e2-e51434989984",
      "name": "irron2004's Projects"
    },
    "id": "29756dd4-c9f5-4771-857b-fe6b607763bd",
    "name": "stellar-fascination",
    "createdAt": "2026-02-14T00:02:47.380Z",
    "updatedAt": "2026-02-14T00:02:52.968Z",
    "deletedAt": null,
    "environments": {
      "edges": [
        {
          "node": {
            "id": "b2d08c05-cbe8-4554-86ab-7e07d1470e1c",
            "name": "production",
            "canAccess": true,
            "serviceInstances": {
              "edges": [
                {
                  "node": {
                    "serviceId": "8be5f68a-13d2-473d-bd87-a7a14eaefe0e"
                  }
                }
              ]
            }
          }
        }
      ]
    },
    "services": {
      "edges": [
        {
          "node": {
            "id": "8be5f68a-13d2-473d-bd87-a7a14eaefe0e",
            "name": "papers"
          }
        }
      ]
    }
  }
]
